[
  {
    "id": "fund_seed_apply",
    "workId": 1,
    "displayName": "기금제도 푸른씨앗 신청하기",
    "menuPath": "홈페이지 > 신청하기 > 가입 > 기금제도 신청하기(사업장)",
    "keywords": [
      "기금제도",
      "푸른씨앗",
      "제도가입",
      "가입",
      "제도신청",
      "신청"
    ],
    "aliases": [
      "기금제도 신청",
      "푸른씨앗 가입",
      "기금제도 가입 절차",
      "기금제도 안내",
      "푸른씨앗 가입 신청"
    ],
    "patterns": [
      "푸른씨앗 신청하고 싶어요",
      "기금제도 가입하려면 어떻게 해요",
      "푸른씨앗 가입 절차 좀 알려주세요",
      "기금제도 신청 어디로 들어가면 돼요?"
    ]
  },
  {
    "id": "staff_register",
    "workId": 2,
    "displayName": "신규직원 등록하기",
    "menuPath": "홈페이지 > 신청하기 > 가입자관리",
    "keywords": [
      "신규직원",
      "직원등록",
      "등록",
      "사람추가",
      "근로자추가",
      "사원추가"
    ],
    "aliases": [
      "직원 추가",
      "직원 등록",
      "신규 직원 입력",
      "근로자 등록",
      "사원 등록"
    ],
    "patterns": [
      "신규 직원 등록하려면 어떻게 해요",
      "직원 새로 추가하는 메뉴가 어디예요?",
      "근로자 등록하려고 하는데 어디서 해요",
      "사원 정보 처음 넣는 거 알려줄래요?"
    ]
  },
  {
    "id": "salary_update",
    "workId": 3,
    "displayName": "급여변경하기",
    "menuPath": "홈페이지 > 신청하기 > 부담금 > 가입자 연간(예상)임금총액변경",
    "keywords": [
      "급여변경",
      "급여수정",
      "연봉변경",
      "월급변경",
      "임금총액",
      "임금총액변경",
      "월급수정",
      "호봉변경",
      "호봉수정"
    ],
    "aliases": [
      "급여 수정",
      "월급 조정",
      "연봉 바꾸기",
      "임금 총액 변경",
      "예상 임금 바꾸기",
      "육아기 근로 단축",
      "무급 휴직",
      "유급 휴직"
    ],
    "patterns": [
      "급여 변경 어디서 할 수 있어요",
      "월급 금액 수정하려면 어떻게 해야 돼요?",
      "연봉 바꾸는 메뉴 알려주세요",
      "임금총액 변경 신청하려고요",
      "호봉 변경하려고",
      "이번 달 호봉이 바뀌었어요",
      "휴직해서 급여가 바뀌었어요",
      "육아기 근로단축 하는데",
      "유급 휴직인데 어떻게"
    ]
  },
  {
    "id": "retire_payout_apply",
    "workId": 4,
    "displayName": "퇴사 - 지급신청",
    "menuPath": "홈페이지 > 신청하기 > 지급 > 퇴직급여 지급신청",
    "keywords": [
      "퇴사",
      "퇴직금",
      "지급신청",
      "퇴직급여",
      "퇴직급여신청",
      "퇴직금신청"
    ],
    "aliases": [
      "퇴직금 지급 신청",
      "퇴직급여 신청",
      "퇴사 지급 안내",
      "퇴직급여 청구",
      "퇴직급여 지급 요청"
    ],
    "patterns": [
      "퇴직금 신청하고 싶은데 어디서 해요?",
      "퇴사 처리할 때 지급 신청은 어떻게 해요",
      "퇴직급여 지급 신청 방법 알려주세요",
      "퇴직금 청구하려면 뭐부터 하면 돼요?"
    ]
  },
  {
    "id": "retire_payout_status",
    "workId": 5,
    "displayName": "퇴사 - 지급신청현황",
    "menuPath": "홈페이지 > 조회하기 > 지급",
    "keywords": [
      "지급신청현황",
      "신청현황",
      "지급현황",
      "퇴직급여진행",
      "퇴직금상태"
    ],
    "aliases": [
      "퇴직금 신청 현황",
      "지급 신청 조회",
      "퇴직급여 진행상황",
      "퇴사 지급 상태 확인",
      "퇴직급여 처리 상태"
    ],
    "patterns": [
      "퇴직금 신청 현황 보고 싶어요",
      "퇴직급여 지금 어디까지 처리됐는지 볼 수 있어요?",
      "지급 신청 상태 어디서 확인하나요",
      "퇴사 지급 처리 상황 좀 알려줄래요?",
      "언제 돈 주나요", "언제 돈 지급되나요",
      "퇴사했는데 퇴직금 언제 되나요",
      "근로자 동의 했는데 지급 언제 되나요",
      "퇴직금 언제 주나요"
    ]
  },
  {
    "id": "occasional_payment",
    "workId": 6,
    "displayName": "사용자 납입 희망 금액 수시납부 처리하기",
    "menuPath": "홈페이지 > 신청하기 > 부담금 > 부담금 수시납입 > 수시납입신청",
    "keywords": [
      "수시납부",
      "수시납입",
      "납입신청",
      "부담금수시",
      "추가납부",
      "희망금액납부"
    ],
    "aliases": [
      "수시 납부 신청",
      "수시 납입 처리",
      "희망 금액 납입",
      "바로 납부하기",
      "즉시 납입 신청"
    ],
    "patterns": [
      "수시로 납입하려면 어디서 신청해요?",
      "희망 금액 수시 납부 처리하고 싶어요",
      "추가로 부담금 지금 바로 넣고 싶은데 가능해요?",
      "수시납입 신청 방법 안내해 주세요"
    ]
  },
  {
    "id": "deposit_amount_change",
    "workId": 7,
    "displayName": "사용자 납입 희망 금액 변경하기",
    "menuPath": "홈페이지 > 신청하기 > 부담금 > 부담금 수시납입 > 정기부담금 납입희망금액 변경신청",
    "keywords": [
      "납입희망금액변경",
      "희망금액변경",
      "납입금액변경",
      "정기납입금액",
      "정기납입금액변경"
    ],
    "aliases": [
      "납입 금액 변경",
      "희망 납입액 수정",
      "정기 납입액 바꾸기",
      "부담금 금액 조정",
      "납부 금액 바꾸기"
    ],
    "patterns": [
      "정기 납입 금액 바꾸고 싶은데요",
      "희망 납입액 수정은 어디서 해요?",
      "납입 금액 변경 신청하려면 어떻게 하면 돼요",
      "부담금 매달 내는 금액을 조정하고 싶어요"
    ]
  },
  {
    "id": "past_lump_sum",
    "workId": 8,
    "displayName": "(과거분) 일시전환부담금 납입신청",
    "menuPath": "홈페이지 > 신청하기 > 부담금 > 일시전환부담금 납입신청",
    "keywords": [
      "과거분",
      "일시전환부담금",
      "일시전환",
      "과거금액",
      "과거납입"
    ],
    "aliases": [
      "과거분 일시 전환 신청",
      "일시전환 부담금 납부",
      "과거 금액 전환",
      "과거분 납입 안내",
      "예전 금액 정산",
      "과거 근로 기간"
    ],
    "patterns": [
      "과거분 일시 전환 신청하려고요",
      "일시전환 부담금 납입은 어디서 하나요",
      "예전 금액 한 번에 내고 싶은데 어떻게 해요?",
      "과거분 납입 처리 방법 좀 알려주세요",
      "과거 근로 기간 처리 방법"
    ]
  },
  {
    "id": "annual_settlement",
    "workId": 9,
    "displayName": "(해당기간 ~ 연 1회) 부담금 정산신청하기",
    "menuPath": "홈페이지 > 신청하기 > 부담금 > 부담금 정산신청",
    "keywords": [
      "정산신청",
      "정산",
      "부담금정산",
      "연간정산",
      "부담금정산신청"
    ],
    "aliases": [
      "부담금 정산 신청",
      "정산 처리",
      "연간 정산 안내",
      "부담금 정산 방법",
      "정산 한번에 신청",
      "차액 정산"
    ],
    "patterns": [
      "부담금 정산 신청하고 싶어요",
      "연간 정산은 어디서 해요?",
      "정산 신청 메뉴 좀 찾아줘",
      "부담금 정산 절차 알려주세요",
      "정산 한 번만 하면 되는 거 맞죠?"
    ]
  },
  {
    "id": "auto_transfer",
    "workId": 10,
    "displayName": "자동이체관리",
    "menuPath": "홈페이지 > 신청하기 > 부담금 > 자동이체관리",
    "keywords": [
      "자동이체",
      "이체관리",
      "자동이체관리",
      "자동납부",
      "계좌등록"
    ],
    "aliases": [
      "자동 이체 설정",
      "부담금 자동이체",
      "자동이체 해지",
      "자동이체 변경",
      "자동 이체 계좌 수정"
    ],
    "patterns": [
      "자동이체 설정하려면 어디로 가면 돼요?",
      "부담금 자동이체 등록하고 싶어요",
      "자동이체 해지는 어디서 해요",
      "자동이체 계좌 바꾸는 메뉴 알려주세요",
      "자동이체로 바꾸고 싶어요",
      "자동이체로 납부하고 싶어요",
      "자동이체 그만하고 싶어요",
      "자동이체 해지할래요",
      "자동이체되는 계좌 바꾸고 싶어요"
    ]
  },
  {
    "id": "info_change",
    "workId": 11,
    "displayName": "기타사항 변경 (근로자 정보, 퇴직급여 담당자 변경)",
    "menuPath": "근로자 정보 변경 : 신청하기 > 가입자 관리 / 퇴직급여 담당자 변경 : 신청하기 > 퇴직급여담당자 관리",
    "keywords": [
      "근로자정보변경",
      "퇴직급여담당자변경",
      "정보변경",
      "담당자변경",
      "사원정보수정"
    ],
    "aliases": [
      "근로자 정보 수정",
      "퇴직급여 담당자 바꾸기",
      "담당자 변경",
      "사원 정보 변경",
      "퇴직 담당자 수정"
    ],
    "patterns": [
      "근로자 정보 바꾸고 싶어요",
      "퇴직급여 담당자 이름 바꿔야 하는데 어디서 바꿔요?",
      "사원 정보 수정 메뉴 찾아주세요",
      "담당자 변경은 어디로 들어가요?"
    ]
  },
  {
    "id": "online_status",
    "workId": 12,
    "displayName": "온라인 신청 현황",
    "menuPath": "홈페이지 > 조회하기 > 가입 > 서류등록현황",
    "keywords": [
      "온라인신청현황",
      "신청현황",
      "처리현황",
      "서류등록현황",
      "접수상태"
    ],
    "aliases": [
      "온라인 신청 상태",
      "전자 신청 현황",
      "신청 처리 현황",
      "서류 등록 확인",
      "접수 내역 확인"
    ],
    "patterns": [
      "온라인으로 넣은 신청 어디까지 됐는지 볼 수 있어요?",
      "지금 신청 처리 현황 확인하고 싶어요",
      "서류 등록된 거 조회하려면 어디 가요?",
      "온라인 신청 상태 알려줘요",
      "내 신청 접수됐는지 확인하고 싶어요"
    ]
  },
  {
    "id": "deposit_statement",
    "workId": 13,
    "displayName": "부담금 납입 안내 (명세서)",
    "menuPath": "홈페이지 > 조회하기 > 부담금 > 부담금납입 안내",
    "keywords": [
      "납입안내",
      "납입명세서",
      "명세서",
      "납부명세서",
      "부담금안내"
    ],
    "aliases": [
      "부담금 명세서",
      "납부 내역 안내",
      "납입 안내서",
      "납부 명세서 출력",
      "부담금 고지서"
    ],
    "patterns": [
      "부담금 납입 명세서 보고 싶어요",
      "납부 명세서 어디서 확인해요?",
      "부담금 안내서 출력하려면 어떻게 해요",
      "이번 달 얼마나 내라고 돼 있는지 볼 수 있나요?"
    ]
  },
  {
    "id": "deposit_history",
    "workId": 14,
    "displayName": "부담금 납입 내역 (기존 납입 내역)",
    "menuPath": "홈페이지 > 조회하기 > 부담금 > 부담금납입 내역",
    "keywords": [
      "납입내역",
      "납부내역",
      "기존납입내역",
      "부담금납부내역",
      "이전납부",
      "납부명세서"
    ],
    "aliases": [
      "기존 납입 내역",
      "지난 납부 내역",
      "납입 기록",
      "부담금 납부 내역",
      "지급했던 내역"
    ],
    "patterns": [
      "지난 납부 내역 확인하고 싶어요",
      "기존 부담금 납부 내역 어디서 봐요?",
      "전에 얼마나 냈는지 조회하고 싶어요",
      "납입 기록 확인 메뉴 알려주세요",
      "몇월달에 낸 기록 확인",
      "돈 냈던거 확인하고 싶어요"
    ]
  },
  {
    "id": "subsidy_result",
    "workId": 15,
    "displayName": "재정지원금 - 지원금 신청결과",
    "menuPath": "홈페이지 > 조회하기 > 부담금 > 재정지원금 신청결과",
    "keywords": [
      "재정지원금",
      "지원금신청결과",
      "신청결과",
      "지원금결과",
      "지원결과"
    ],
    "aliases": [
      "지원금 신청 결과",
      "재정 지원 결과",
      "지원금 결과 확인",
      "재정지원 결과 조회",
      "지원 승인 여부"
    ],
    "patterns": [
      "지원금 신청 결과 어디서 확인해요?",
      "재정지원금 승인됐는지 보고 싶어요",
      "지원금 결과 조회 어떻게 하죠",
      "신청 결과 나왔는지 알려줄래요?"
    ]
  },
  {
    "id": "subsidy_payment_history",
    "workId": 16,
    "displayName": "재정지원금 - 지원금 지급내역",
    "menuPath": "홈페이지 > 조회하기 > 부담금 > 재정지원금 지급내역",
    "keywords": [
      "재정지원금",
      "지원금지급내역",
      "지원금내역",
      "지급내역",
      "지원금지급"
    ],
    "aliases": [
      "지원금 지급 내역",
      "재정지원금 지급 기록",
      "지원금 받은 내역",
      "재정 지원금 내역",
      "지급된 금액 조회"
    ],
    "patterns": [
      "지원금 지급 내역 확인하고 싶어요",
      "재정지원금 얼마 들어왔는지 보고 싶어요",
      "지원금 받은 내역 어디서 봐요",
      "지급된 금액 조회할 수 있나요",
      "지원금이 들어왔는데 뭔가요"
    ]
  },
  {
    "id": "certificate_issue",
    "workId": 17,
    "displayName": "증명서 발급",
    "menuPath": "홈페이지 > 조회하기 > 증명서발급",
    "keywords": [
      "증명서발급",
      "증명서",
      "발급",
      "영수증",
      "확인서",
      "명세서",
      "제증명"
    ],
    "aliases": [
      "증명서 출력",
      "증명서 신청",
      "증명서 발급 안내",
      "증명서 발급하고 싶어요",
      "증빙서류 발급",
      "제증명 발급"
    ],
    "patterns": [
      "증명서 발급하려면 어떻게 해요?",
      "증명서 바로 출력할 수 있어요?",
      "증빙서류 뽑고 싶은데 어디 가면 돼요",
      "확인서 발급 메뉴 알려주세요",
      "납입 확인서 같은 거 출력 가능해요?"
    ]
  },
  {
    "id": "form_library",
    "workId": 18,
    "displayName": "서식 자료실",
    "menuPath": "홈페이지 > 고객센터 > 서식자료실",
    "keywords": [
      "서식자료실",
      "서식",
      "자료실",
      "양식",
      "서류양식",
      "다운로드서류",
      "종이서류"
    ],
    "aliases": [
      "서식 다운로드",
      "양식 자료실",
      "필요 서류 찾기",
      "서류 양식 모음",
      "필수 서식 모음"
    ],
    "patterns": [
      "서식 자료실 어디 있어요?",
      "필요한 양식 다운로드하려면 어디 가요?",
      "퇴직 관련 서류 양식 찾고 싶은데요",
      "신청서 서식 다운받을 수 있는 데 알려주세요",
      "양식 모아놓은 곳 연결해줘요",
      "종이 서류 필요해요",
      "서면 신청하려고 해요"
    ]
  }
]